DUELink/Analog.py
DUELink/Button.py
DUELink/DMX.py
DUELink/DUELinkController.py
DUELink/DeviceConfiguration.py
DUELink/Digital.py
DUELink/DistanceSensor.py
DUELink/Engine.py
DUELink/FileSystem.py
DUELink/Frequency.py
DUELink/Graphics.py
DUELink/GraphicsType.py
DUELink/Humidity.py
DUELink/I2C.py
DUELink/Infrared.py
DUELink/Otp.py
DUELink/Pulse.py
DUELink/Rtc.py
DUELink/SerialInterface.py
DUELink/Servo.py
DUELink/Sound.py
DUELink/Spi.py
DUELink/Stream.py
DUELink/System.py
DUELink/Temperature.py
DUELink/Uart.py
DUELink/__init__.py
duelink-1.2.3.dist-info/METADATA
duelink-1.2.3.dist-info/WHEEL
duelink-1.2.3.dist-info/top_level.txt
duelink-1.2.3.dist-info/RECORD
