Metadata-Version: 2.1
Name: duelink
Version: 1.2.3
Summary: GHI Electronics DUELink Python library.
Home-page: https://www.duelink.com/
Author: GHI Electronics
Author-email: support@ghielectronics.com
License: MIT
Classifier: Programming Language :: Python :: 3
Classifier: Operating System :: OS Independent
Requires-Python: >=3.6
Requires-Dist: pyserial
